{
  "title": "Schedule",
  "slug": "schedule",
  "talks": [
    {
      "title": "Intro",
      "time": ["8:30", "9:00"]
    }, {
      "speaker": "justin",
      "time": ["9:00", "9:30"]
    }, {
      "speaker": "takuya",
      "time": ["9:35", "9:45"],
      "type": "lightning"
    }, {
      "speaker": "bjorn",
      "time": ["9:50", "10:20"]
    }, {
      "speaker": "hao",
      "time": ["10:25", "10:35"],
      "type": "lightning"
    }, {
      "speaker": "maria",
      "time": ["10:40", "11:10"]
    }, {
      "speaker": "evgeni",
      "time": ["11:15", "11:25"],
      "type": "lightning"
    }, {
      "speaker": "famiu",
      "time": ["11:30", "12:00"]
    }, {
      "speaker": "joshmedeski",
      "time": ["12:05", "12:10"],
      "type": "lightning"
    }, {
      "speaker": "gregoryanders",
      "time": ["12:10", "12:28"]
    }, {
      "speaker": "mikesmith",
      "time": ["12:30", "12:40"],
      "type": "lightning"
    }, {
      "speaker": "teej",
      "time": ["12:45", "13:15"]
    }, {
      "speaker": "johnmcbride",
      "time": ["13:15", "13:25"],
      "type": "lightning"
    }, {
      "speaker": "mathewpayne",
      "time": ["13:25", "13:35"],
      "type": "lightning"
    }, {
      "speaker" : "kewbish",
      "time": ["13:35", "13:25"],
      "type": "lightning"
    }, {
      "speaker": "jesseleite",
      "time": ["13:45", "13:55"],
      "type": "lightning"
    }, {
      "time": ["13:50", "14:35"],
      "title": "Fireside chat with TeeJ and The Primeagen"
    }
  ]
}
